cscopy/__init__.py
cscopy/cli.py
cscopy/model.py
cscopy/workspace.py
cscopy/utils/common.py
cscopy-0.0.3.dist-info/LICENSE
cscopy-0.0.3.dist-info/METADATA
cscopy-0.0.3.dist-info/WHEEL
cscopy-0.0.3.dist-info/top_level.txt
cscopy-0.0.3.dist-info/RECORD
