Metadata-Version: 2.1
Name: cscopy
Version: 0.0.3
Summary: Python binding for cscopy
Author-email: jingfelix <jingfelix@outlook.com>
License: MIT
Requires-Python: >=3.10
License-File: LICENSE
Requires-Dist: pydantic>=2.7.3
